piesparrow/__init__.py
piesparrow/piesparrow.py
piesparrow/pspchart.py
piesparrow/pspdonut.py
piesparrow/pspgauge.py
piesparrow/pspkpi.py
piesparrow/psppie.py
piesparrow/psptable.py
piesparrow/psptypo.py
piesparrow-0.1.2.dist-info/LICENSE
piesparrow-0.1.2.dist-info/METADATA
piesparrow-0.1.2.dist-info/WHEEL
piesparrow-0.1.2.dist-info/top_level.txt
piesparrow-0.1.2.dist-info/RECORD
